taoswswrap/__init__.py
taoswswrap/tdengine_connection.py
taoswswrap-0.3.5.dist-info/licenses/LICENSE
taoswswrap-0.3.5.dist-info/METADATA
taoswswrap-0.3.5.dist-info/WHEEL
taoswswrap-0.3.5.dist-info/top_level.txt
taoswswrap-0.3.5.dist-info/RECORD
